apier_bridge/__init__.py
apier_bridge/base.py
apier_bridge/eastmoney.py
apier_bridge/utils/file.py
apier_bridge-0.0.3.dist-info/METADATA
apier_bridge-0.0.3.dist-info/WHEEL
apier_bridge-0.0.3.dist-info/licenses/LICENSE
apier_bridge-0.0.3.dist-info/RECORD
