Metadata-Version: 2.1
Name: apier_bridge
Version: 0.0.3
Summary: A bridge -- api collection for python
Author-email: camel lu <luxuemin2108@gmail.com>
License-File: LICENSE
Classifier: License :: OSI Approved :: MIT License
Classifier: Operating System :: OS Independent
Classifier: Programming Language :: Python :: 3
Requires-Python: >=3.7
